txradius/__init__.py
txradius/authorize.py
txradius/client.py
txradius/message.py
txradius/radtest.py
txradius/statistics.py
txradius/dictionary/dictionary
txradius/dictionary/dictionary.3com
txradius/dictionary/dictionary.3gpp
txradius/dictionary/dictionary.3gpp2
txradius/dictionary/dictionary.acc
txradius/dictionary/dictionary.acme
txradius/dictionary/dictionary.airespace
txradius/dictionary/dictionary.alcatel
txradius/dictionary/dictionary.alcatel.esam
txradius/dictionary/dictionary.alcatel.sr
txradius/dictionary/dictionary.alteon
txradius/dictionary/dictionary.altiga
txradius/dictionary/dictionary.alvarion
txradius/dictionary/dictionary.apc
txradius/dictionary/dictionary.aptis
txradius/dictionary/dictionary.aruba
txradius/dictionary/dictionary.ascend
txradius/dictionary/dictionary.asn
txradius/dictionary/dictionary.attingo
txradius/dictionary/dictionary.audiocodes
txradius/dictionary/dictionary.avaya
txradius/dictionary/dictionary.azaire
txradius/dictionary/dictionary.bay
txradius/dictionary/dictionary.bintec
txradius/dictionary/dictionary.bristol
txradius/dictionary/dictionary.cablelabs
txradius/dictionary/dictionary.cabletron
txradius/dictionary/dictionary.chillispot
txradius/dictionary/dictionary.cisco
txradius/dictionary/dictionary.cisco.bbsm
txradius/dictionary/dictionary.cisco.vpn3000
txradius/dictionary/dictionary.cisco.vpn5000
txradius/dictionary/dictionary.clavister
txradius/dictionary/dictionary.colubris
txradius/dictionary/dictionary.columbia_university
txradius/dictionary/dictionary.compat
txradius/dictionary/dictionary.coova
txradius/dictionary/dictionary.cosine
txradius/dictionary/dictionary.dhcp
txradius/dictionary/dictionary.digest
txradius/dictionary/dictionary.digium
txradius/dictionary/dictionary.epygi
txradius/dictionary/dictionary.ericsson
txradius/dictionary/dictionary.erx
txradius/dictionary/dictionary.extreme
txradius/dictionary/dictionary.fortinet
txradius-1.0.5.dist-info/DESCRIPTION.rst
txradius-1.0.5.dist-info/eager_resources.txt
txradius-1.0.5.dist-info/entry_points.txt
txradius-1.0.5.dist-info/METADATA
txradius-1.0.5.dist-info/metadata.json
txradius-1.0.5.dist-info/RECORD
txradius-1.0.5.dist-info/top_level.txt
txradius-1.0.5.dist-info/WHEEL
txradius-1.0.5.dist-info/zip-safe
