Metadata-Version: 2.0
Name: txradius
Version: 1.0.5
Summary: RADIUS tools
Home-page: https://github.com/talkincode/txradius
Author: jamiesun
Author-email: jamiesun.net@gmail.com
License: LGPL
Keywords: radius,AAA,authentication,accounting,authorization,toughradius
Platform: UNKNOWN
Classifier: Development Status :: 6 - Mature
Classifier: Intended Audience :: Developers
Classifier: Programming Language :: Python :: 2.6
Classifier: Programming Language :: Python :: 2.7
Classifier: Topic :: Software Development :: Libraries :: Python Modules
Classifier: Topic :: System :: Systems Administration :: Authentication/Directory
Requires-Dist: six (>=1.8.0)
Requires-Dist: Twisted (>=15.0.0)
Requires-Dist: Click
